odoo/addons/product_seasonality/README.rst
odoo/addons/product_seasonality/__init__.py
odoo/addons/product_seasonality/__manifest__.py
odoo/addons/product_seasonality/i18n/fr.po
odoo/addons/product_seasonality/i18n/product_seasonality.pot
odoo/addons/product_seasonality/migrations/14.0.1.1.0/post-migration.py
odoo/addons/product_seasonality/models/__init__.py
odoo/addons/product_seasonality/models/res_company.py
odoo/addons/product_seasonality/models/res_partner.py
odoo/addons/product_seasonality/models/seasonal_config.py
odoo/addons/product_seasonality/models/seasonal_config_line.py
odoo/addons/product_seasonality/readme/CONFIGURE.rst
odoo/addons/product_seasonality/readme/CONTRIBUTORS.rst
odoo/addons/product_seasonality/readme/DESCRIPTION.rst
odoo/addons/product_seasonality/security/ir.model.access.csv
odoo/addons/product_seasonality/static/description/icon.png
odoo/addons/product_seasonality/static/description/index.html
odoo/addons/product_seasonality/tests/__init__.py
odoo/addons/product_seasonality/tests/common.py
odoo/addons/product_seasonality/tests/test_company.py
odoo/addons/product_seasonality/tests/test_seasonal_config.py
odoo/addons/product_seasonality/views/res_company.xml
odoo/addons/product_seasonality/views/res_partner.xml
odoo/addons/product_seasonality/views/seasonal_config.xml
odoo/addons/product_seasonality/views/seasonal_config_line.xml
odoo14_addon_product_seasonality-14.0.1.3.0.dist-info/METADATA
odoo14_addon_product_seasonality-14.0.1.3.0.dist-info/WHEEL
odoo14_addon_product_seasonality-14.0.1.3.0.dist-info/top_level.txt
odoo14_addon_product_seasonality-14.0.1.3.0.dist-info/RECORD
